wappstoiot/__init__.py
wappstoiot/py.typed
wappstoiot/connections/__init__.py
wappstoiot/connections/protocol.py
wappstoiot/connections/sslsocket.py
wappstoiot/modules/__init__.py
wappstoiot/modules/device.py
wappstoiot/modules/network.py
wappstoiot/modules/template.py
wappstoiot/modules/value.py
wappstoiot/schema/__init__.py
wappstoiot/schema/base_schema.py
wappstoiot/schema/iot_schema.py
wappstoiot/service/__init__.py
wappstoiot/service/iot_api.py
wappstoiot/service/template.py
wappstoiot/utils/Timestamp.py
wappstoiot/utils/__init__.py
wappstoiot/utils/certificateread.py
wappstoiot/utils/jitter.py
wappstoiot/utils/name_check.py
wappstoiot/utils/observer.py
wappstoiot/utils/offline_storage.py
wappstoiot/utils/period.py
wappstoiot-0.8.0.dist-info/LICENSE
wappstoiot-0.8.0.dist-info/METADATA
wappstoiot-0.8.0.dist-info/WHEEL
wappstoiot-0.8.0.dist-info/top_level.txt
wappstoiot-0.8.0.dist-info/RECORD
