Metadata-Version: 2.1
Name: wappstoiot
Version: 0.8.0
Summary: Simple Wappsto Python user-interface to Wappsto IoT
Home-page: https://github.com/Wappsto/python-wappsto-iot
Author: Seluxit A/S
Author-email: support@seluxit.com
License: Apache-2.0
Classifier: Programming Language :: Python :: 3.7
Classifier: Programming Language :: Python :: 3.8
Classifier: Programming Language :: Python :: 3.9
Classifier: Programming Language :: Python :: 3.10
Classifier: Programming Language :: Python :: 3.11
Classifier: Operating System :: OS Independent
Requires-Python: >=3.7.0
License-File: LICENSE
Requires-Dist: slxjsonrpc (>=0.9.2)
Requires-Dist: pydantic (<3.0.0,>=2.0.0)
